[
  {
    "family": "brother-1816-printed",
    "weight": "400",
    "style": "italic"
  },
  {
    "family": "brother-1816-printed",
    "weight": "400",
    "style": "normal"
  },
  {
    "family": "brother-1816-printed",
    "weight": "700",
    "style": "italic"
  },
  {
    "family": "brother-1816-printed",
    "weight": "700",
    "style": "normal"
  },
  {
    "family": "slick",
    "weight": "normal",
    "style": "normal"
  },
  {
    "family": "Font Awesome 5 Brands",
    "weight": "400",
    "style": "normal"
  },
  {
    "family": "Font Awesome 5 Free",
    "weight": "900",
    "style": "normal"
  },
  {
    "family": "Font Awesome 5 Free",
    "weight": "400",
    "style": "normal"
  },
  {
    "family": "FontAwesome",
    "weight": "normal",
    "style": "normal"
  },
  {
    "family": "FontAwesome",
    "weight": "normal",
    "style": "normal"
  },
  {
    "family": "FontAwesome",
    "weight": "normal",
    "style": "normal"
  },
  {
    "family": "FontAwesome",
    "weight": "normal",
    "style": "normal"
  },
  {
    "family": "brother-1816",
    "weight": "400",
    "style": "italic"
  },
  {
    "family": "brother-1816",
    "weight": "400",
    "style": "normal"
  },
  {
    "family": "brother-1816",
    "weight": "700",
    "style": "italic"
  },
  {
    "family": "brother-1816",
    "weight": "700",
    "style": "normal"
  },
  {
    "family": "Font Awesome 6 Brands",
    "weight": "400",
    "style": "normal"
  },
  {
    "family": "Font Awesome 6 Free",
    "weight": "400",
    "style": "normal"
  },
  {
    "family": "Font Awesome 6 Free",
    "weight": "900",
    "style": "normal"
  },
  {
    "family": "Rubik",
    "weight": "500",
    "style": "normal"
  },
  {
    "family": "Rubik",
    "weight": "400",
    "style": "normal"
  }
]